canadatestgen/__init__.py
canadatestgen/cli.py
canadatestgen/core.py
canadatestgen/schema_loader.py
canadatestgen-0.1.3.dist-info/licenses/LICENSE
canadatestgen-0.1.3.dist-info/METADATA
canadatestgen-0.1.3.dist-info/WHEEL
canadatestgen-0.1.3.dist-info/entry_points.txt
canadatestgen-0.1.3.dist-info/top_level.txt
canadatestgen-0.1.3.dist-info/RECORD
