Metadata-Version: 2.4
Name: canadatestgen
Version: 0.1.3
Summary: Generate fake Canadian-style test data with a simple CLI or Python module.
Home-page: https://github.com/GuiNom16/canadatestgen
Author: Jeremie Nombro
Author-email: Your Name <you@example.com>
License-Expression: MIT
Requires-Python: >=3.8
License-File: LICENSE
Dynamic: author
Dynamic: home-page
Dynamic: license-file
Dynamic: requires-python
